{
  "flower": "ALL",
  "maxTimeInHive": 600,
  "hasHoneycomb": true,
  "baseLayerTexture": "stones/custom/lumber_bee",
  "ColorData": {
    "isBeeColored": false,
    "primaryColor": "#594529",
	"secondaryColor": "#A0824E",
    "honeycombColor": "#594529"
  },
  "MutationData": {
    "hasMutation": false
  },
  "CentrifugeData": {
    "hasCentrifugeOutput": true,
    "mainOutput": "minecraft:oak_log",
    "bottleOutputWeight": 0.15,
    "mainOutputCount": 2
  },
  "SpawnData": {
    "canSpawnInWorld": true,
    "biomeWhitelist": "tag:forest"
  },
  "BreedData": {
    "isBreedable": true,
    "feedItem": "tag:minecraft:logs",
    "feedAmount": 4
  },
  "TraitData": {
    "hasTraits": false
  }
}
