{
  "flower": "tag:forge:storage_blocks/enderium",
  "hasHoneycomb": true,
  "maxTimeInHive": 600,
  "baseLayerTexture": "/ores/custom/custom_bee",
  "ColorData": {
    "isBeeColored": true,
    "honeycombColor": "#2BA6AD",
    "primaryColor": "#ffffff",
    "secondaryColor": "#2BA6AD",
    "primaryLayerTexture": "/ores/custom/custom_bee_primary",
    "secondaryLayerTexture": "/ores/custom/custom_bee_secondary",
    "modelType": "ORE"
  },
  "MutationData": {
    "hasMutation": true,
    "mutationInput": "jaopca:storage_blocks.ender_pearl",
    "mutationOutput": "thermal:enderium_block",
    "mutationType": "BLOCK_TO_BLOCK"
  },
  "CentrifugeData": {
    "hasCentrifugeOutput": false
  },
  "SpawnData": {
    "canSpawnInWorld": false
  },
  "BreedData": {
    "isBreedable": true,
    "parent1": "Diamond, Diamond",
    "parent2": "Lead, Ender",
    "feedItem": "forge:ingots/enderium",
    "feedAmount": 2
  },
  "TraitData": {
    "hasTraits": true
  }
}